removebg_cli.py
removebg_cli-1.0.0.dist-info/METADATA
removebg_cli-1.0.0.dist-info/WHEEL
removebg_cli-1.0.0.dist-info/entry_points.txt
removebg_cli-1.0.0.dist-info/top_level.txt
removebg_cli-1.0.0.dist-info/RECORD
