Metadata-Version: 2.4
Name: removebg-cli
Version: 1.0.0
Summary: 智能图片背景移除命令行工具 (remove.bg API)
License: MIT
Project-URL: Homepage, https://github.com/jiasunm/removebg-cli
Keywords: remove background,image,cli,remove.bg
Requires-Python: >=3.8
Requires-Dist: requests>=2.20
Requires-Dist: rich>=10.0
